s3_data_packer/__init__.py
s3_data_packer/constants.py
s3_data_packer/helpers.py
s3_data_packer/s3_data_packer.py
s3_data_packer/s3_output_store.py
s3_data_packer/s3_table_store.py
s3_data_packer-0.0.9.dist-info/METADATA
s3_data_packer-0.0.9.dist-info/WHEEL
s3_data_packer-0.0.9.dist-info/RECORD
