Metadata-Version: 2.1
Name: s3_data_packer
Version: 0.0.9
Summary: 
License: MIT
Author: s-ducks
Author-email: stephen.bias@digital.justice.gov.uk
Requires-Python: >=3.8,<4
Classifier: License :: OSI Approved :: MIT License
Classifier: Programming Language :: Python :: 3
Classifier: Programming Language :: Python :: 3.8
Classifier: Programming Language :: Python :: 3.9
Classifier: Programming Language :: Python :: 3.10
Classifier: Programming Language :: Python :: 3.11
Classifier: Programming Language :: Python :: 3.12
Requires-Dist: arrow-pd-parser (>=1.3.0)
Requires-Dist: awswrangler (>=2.12.0)
Requires-Dist: dataengineeringutils3 (>=1.2.1,<2.0.0)
Requires-Dist: mojap-metadata (>=1.10.0,<2.0.0)
Requires-Dist: numpy (>=1.22,<2.0)
